TkLiteUI.py
__init__.py
TkLiteUI-0.9.dist-info/LICENSE
TkLiteUI-0.9.dist-info/METADATA
TkLiteUI-0.9.dist-info/WHEEL
TkLiteUI-0.9.dist-info/top_level.txt
TkLiteUI-0.9.dist-info/RECORD
