Metadata-Version: 2.1
Name: TkLiteUI
Version: 0.9
Summary: Kolay bir Tkinter kullanıcı arayüz kütüphanesi
Author-email: Adem Ulker <ademulker055@gmail.com>
License: MIT License
Keywords: tkinter,GUI,user interface
Classifier: Programming Language :: Python :: 3
Classifier: Programming Language :: Python :: 3.6
Classifier: Programming Language :: Python :: 3.7
Classifier: Programming Language :: Python :: 3.8
Classifier: Programming Language :: Python :: 3.9
Classifier: License :: OSI Approved :: MIT License
Classifier: Operating System :: OS Independent
Requires-Python: >=3.0
License-File: LICENSE
